dotchain/__init__.py
dotchain/chain.py
dotchain/dot_chain.py
dotchain-0.0.1.dist-info/METADATA
dotchain-0.0.1.dist-info/WHEEL
dotchain-0.0.1.dist-info/licenses/LICENSE
dotchain-0.0.1.dist-info/RECORD
