Metadata-Version: 2.1
Name: dotchain
Version: 0.0.1
Summary: Python method chaining and piping with asyncio support.
Project-URL: repository, https://github.com/pcstout/dotchain
License-File: LICENSE
Classifier: License :: OSI Approved :: Apache Software License
Classifier: Operating System :: OS Independent
Classifier: Programming Language :: Python
Classifier: Programming Language :: Python :: 3.10
Classifier: Programming Language :: Python :: 3.11
Requires-Python: >=3.10
